ugecko/__init__.py
ugecko/uGecko.py
ugecko/enums/Commands.py
ugecko/utils/Errors.py
ugecko/utils/Memory.py
ugecko/utils/Verification.py
ugecko-1.3.2.dist-info/LICENSE
ugecko-1.3.2.dist-info/METADATA
ugecko-1.3.2.dist-info/WHEEL
ugecko-1.3.2.dist-info/top_level.txt
ugecko-1.3.2.dist-info/RECORD
