Metadata-Version: 2.1
Name: ugecko
Version: 1.3.2
Summary: Python library for use with TCPGecko. Requires kernel exploit to use.
Home-page: https://github.com/vincent-coding/uGecko
Author: WiiuDev, VCoding
License: MIT
Project-URL: Source Code, https://github.com/vincent-coding/uGecko
Project-URL: Documentation, https://github.com/vincent-coding/uGecko/tree/master/docs
Project-URL: Issue Tracker, https://github.com/vincent-coding/uGecko/issues
Platform: UNKNOWN
Classifier: Intended Audience :: Developers
Classifier: Natural Language :: English
Classifier: Operating System :: OS Independent
Classifier: Programming Language :: Python :: 3.8
Classifier: Programming Language :: Python :: 3.9
Requires-Python: >=3.8.0
License-File: LICENSE
